meapy/__init__.py
meapy/loadingconfig.py
meapy/meapy.py
meapy/measurement.py
meapy/measurementlist.py
meapy/signaldata.py
meapy-0.0.13.dist-info/METADATA
meapy-0.0.13.dist-info/WHEEL
meapy-0.0.13.dist-info/top_level.txt
meapy-0.0.13.dist-info/RECORD
