Metadata-Version: 2.1
Name: meapy
Version: 0.0.13
Summary: Python API Wrapper for Measurement Data
Home-page: https://bitbucket.chemnitz.kistler.com/projects/MDM/repos/meapy
Download-URL: https://pypi.python.org/pypi/meapy
Author: Philipp Oehme
Author-email: philipp.oehme@kistler.com
Classifier: Development Status :: 3 - Alpha
Classifier: Intended Audience :: Science/Research
Classifier: Intended Audience :: Developers
Classifier: Programming Language :: Python
Classifier: Programming Language :: Python :: 3
Classifier: Programming Language :: Python :: 3.5
Classifier: Programming Language :: Python :: 3.6
Classifier: Programming Language :: Python :: 3.7
Classifier: Programming Language :: Python :: 3.8
Classifier: Programming Language :: Python :: 3 :: Only
Classifier: Operating System :: OS Independent
Classifier: Operating System :: Microsoft :: Windows
Classifier: Operating System :: POSIX
Classifier: Operating System :: Unix
Classifier: Operating System :: MacOS
Classifier: Topic :: Software Development
Classifier: Topic :: Scientific/Engineering
Requires-Python: >=3.5
Requires-Dist: requests
Requires-Dist: uuid
